src/EnCrypt64/__init__.py
src/EnCrypt64/encrypt64.py
EnCrypt64-0.0.1.dist-info/LICENSE
EnCrypt64-0.0.1.dist-info/METADATA
EnCrypt64-0.0.1.dist-info/WHEEL
EnCrypt64-0.0.1.dist-info/top_level.txt
EnCrypt64-0.0.1.dist-info/RECORD
