Metadata-Version: 2.1
Name: EnCrypt64
Version: 0.0.1
Summary: A Encrypting and Decrypting Package
Home-page: https://github.com/Jacoblightning/EnCrypt64
Author: Jacoblightning
Author-email: jacoblightning3 <t00niyf5@duck.com>
License: GNU GENERAL PUBLIC LICENSE
Project-URL: Homepage, https://github.com/Jacoblightning/EnCrypt
Project-URL: Bug Tracker, https://github.com/Jacoblightning/EnCrypt/issues
Classifier: Natural Language :: English
Classifier: Programming Language :: Python :: 3
Classifier: License :: OSI Approved :: MIT License
Classifier: Operating System :: Microsoft :: Windows
Requires-Python: >=3.10
License-File: LICENSE
Requires-Dist: cryptography (==37.0.4)
